requests_ratelimiter/__init__.py
requests_ratelimiter/py.typed
requests_ratelimiter/requests_ratelimiter.py
requests_ratelimiter-0.5.1.dist-info/LICENSE
requests_ratelimiter-0.5.1.dist-info/METADATA
requests_ratelimiter-0.5.1.dist-info/WHEEL
requests_ratelimiter-0.5.1.dist-info/RECORD
